{
    "version": "0.5.5",
    "architecture": {
        "64bit": {
            "url": "https://github.com/bab-sh/bab/releases/download/v0.5.5/bab_0.5.5_Windows_x86_64.zip",
            "bin": [
                "bab.exe"
            ],
            "hash": "a61cf7011d5de695ab610b3a2595947df73e7933f114b1ca36709c09fa3c9184"
        }
    },
    "homepage": "https://github.com/bab-sh/bab",
    "license": "MIT",
    "description": "Task runner for defining project commands in YAML",
    "shortcuts": [
        [
            "bab.exe",
            "Bab CLI"
        ]
    ]
}
