{
    "version": "0.6.1",
    "architecture": {
        "64bit": {
            "url": "https://github.com/bab-sh/bab/releases/download/v0.6.1/bab_0.6.1_Windows_x86_64.zip",
            "bin": [
                "bab.exe"
            ],
            "hash": "2585113c32ec9b4a893133240c3382e53bc9ff448e955211996197a392597b73"
        }
    },
    "homepage": "https://github.com/bab-sh/bab",
    "license": "MIT",
    "description": "Task runner for defining project commands in YAML",
    "shortcuts": [
        [
            "bab.exe",
            "Bab CLI"
        ]
    ]
}
